spb/__init__.py
spb/session.py
spb/command/__init__.py
spb/command/builder.py
spb/command/commands.py
spb/models/__init__.py
spb/models/data.py
spb/models/label.py
spb/models/project.py
spb/orm/__init__.py
spb/orm/loading.py
spb/orm/manager.py
spb/orm/model.py
spb/orm/query.py
spb/orm/type.py
spb/orm/utils.py
cool_tree-0.0.8.dist-info/METADATA
cool_tree-0.0.8.dist-info/WHEEL
cool_tree-0.0.8.dist-info/top_level.txt
cool_tree-0.0.8.dist-info/RECORD
