Metadata-Version: 2.1
Name: cool-tree
Version: 0.0.8
Summary: Suite Standard Library
Home-page: https://github.com/Superb-AI-Suite/cool-tree.git
Author: Superb AI
Author-email: support@superb-ai.com
License: MIT
Platform: UNKNOWN
Classifier: Development Status :: 1 - Planning
Classifier: Intended Audience :: Developers
Classifier: Topic :: Software Development :: Libraries
Classifier: License :: OSI Approved :: MIT License
Classifier: Programming Language :: Python :: 3.6
Requires-Dist: requests
Requires-Dist: stringcase
Requires-Dist: python-datauri
